{
  "template" : "snortids*",
  "version" : 50001,
  "settings" : {
    "index.refresh_interval" : "5s"
  },
  "mappings" : {
    "_default_" : {
        "properties" : {
          "@timestamp" : {
            "type" : "date"
          },
          "@version" : {
            "type" : "text",
            "fields" : {
              "keyword" : {
                "type" : "keyword",
                "ignore_above" : 256
              }
            }
          },
          "Checksum" : {
            "type" : "text",
            "fields" : {
              "keyword" : {
                "type" : "keyword",
                "ignore_above" : 256
              }
            }
          },
          "DstGeoip" : {
            "properties" : {
              "city_name" : {
                "type" : "text",
                "fields" : {
                  "keyword" : {
                    "type" : "keyword",
                    "ignore_above" : 256
                  }
                }
              },
              "continent_code" : {
                "type" : "text",
                "fields" : {
                  "keyword" : {
                    "type" : "keyword",
                    "ignore_above" : 256
                  }
                }
              },
              "coordinates" : {
                "type" : "float"
              },
              "country_code2" : {
                "type" : "text",
                "fields" : {
                  "keyword" : {
                    "type" : "keyword",
                    "ignore_above" : 256
                  }
                }
              },
              "country_code3" : {
                "type" : "text",
                "fields" : {
                  "keyword" : {
                    "type" : "keyword",
                    "ignore_above" : 256
                  }
                }
              },
              "country_name" : {
                "type" : "text",
                "fields" : {
                  "keyword" : {
                    "type" : "keyword",
                    "ignore_above" : 256
                  }
                }
              },
              "dma_code" : {
                "type" : "long"
              },
              "ip" : { "type" : "ip" },
              "latitude" : {
                "type" : "float"
              },
              "location" : { "type" : "geo_point" },
              "longitude" : {
                "type" : "float"
              },
              "postal_code" : {
                "type" : "text",
                "fields" : {
                  "keyword" : {
                    "type" : "keyword",
                    "ignore_above" : 256
                  }
                }
              },
              "region_code" : {
                "type" : "text",
                "fields" : {
                  "keyword" : {
                    "type" : "keyword",
                    "ignore_above" : 256
                  }
                }
              },
              "region_name" : {
                "type" : "text",
                "fields" : {
                  "keyword" : {
                    "type" : "keyword",
                    "ignore_above" : 256
                  }
                }
              },
              "timezone" : {
                "type" : "text",
                "fields" : {
                  "keyword" : {
                    "type" : "keyword",
                    "ignore_above" : 256
                  }
                }
              }
            }
          },
          "DstIp" : { "type" : "ip" },
          "DstPort" : {
            "type" : "long"
          },
          "ET_Signature_Info" : {
            "type" : "text",
            "fields" : {
              "keyword" : {
                "type" : "keyword",
                "ignore_above" : 256
              }
            }
          },
          "FragOffset" : {
            "type" : "text",
            "fields" : {
              "keyword" : {
                "type" : "keyword",
                "ignore_above" : 256
              }
            }
          },
          "IpHeaderLength" : {
            "type" : "text",
            "fields" : {
              "keyword" : {
                "type" : "keyword",
                "ignore_above" : 256
              }
            }
          },
          "IpId" : {
            "type" : "text",
            "fields" : {
              "keyword" : {
                "type" : "keyword",
                "ignore_above" : 256
              }
            }
          },
          "IpReserved" : {
            "type" : "text",
            "fields" : {
              "keyword" : {
                "type" : "keyword",
                "ignore_above" : 256
              }
            }
          },
          "IpTos" : {
            "type" : "text",
            "fields" : {
              "keyword" : {
                "type" : "keyword",
                "ignore_above" : 256
              }
            }
          },
          "IpVersion" : {
            "type" : "text",
            "fields" : {
              "keyword" : {
                "type" : "keyword",
                "ignore_above" : 256
              }
            }
          },
          "PacketLength" : {
            "type" : "text",
            "fields" : {
              "keyword" : {
                "type" : "keyword",
                "ignore_above" : 256
              }
            }
          },
          "Snort_Signature_Info" : {
            "type" : "text",
            "fields" : {
              "keyword" : {
                "type" : "keyword",
                "ignore_above" : 256
              }
            }
          },
          "SrcGeoip" : {
            "properties" : {
              "city_name" : {
                "type" : "text",
                "fields" : {
                  "keyword" : {
                    "type" : "keyword",
                    "ignore_above" : 256
                  }
                }
              },
              "continent_code" : {
                "type" : "text",
                "fields" : {
                  "keyword" : {
                    "type" : "keyword",
                    "ignore_above" : 256
                  }
                }
              },
              "coordinates" : {
                "type" : "float"
              },
              "country_code2" : {
                "type" : "text",
                "fields" : {
                  "keyword" : {
                    "type" : "keyword",
                    "ignore_above" : 256
                  }
                }
              },
              "country_code3" : {
                "type" : "text",
                "fields" : {
                  "keyword" : {
                    "type" : "keyword",
                    "ignore_above" : 256
                  }
                }
              },
              "country_name" : {
                "type" : "text",
                "fields" : {
                  "keyword" : {
                    "type" : "keyword",
                    "ignore_above" : 256
                  }
                }
              },
              "dma_code" : {
                "type" : "long"
              },
              "ip" : { "type" : "ip" },
              "latitude" : {
                "type" : "float"
              },
              "location" : { "type" : "geo_point" },
              "longitude" : {
                "type" : "float"
              },
              "postal_code" : {
                "type" : "text",
                "fields" : {
                  "keyword" : {
                    "type" : "keyword",
                    "ignore_above" : 256
                  }
                }
              },
              "region_code" : {
                "type" : "text",
                "fields" : {
                  "keyword" : {
                    "type" : "keyword",
                    "ignore_above" : 256
                  }
                }
              },
              "region_name" : {
                "type" : "text",
                "fields" : {
                  "keyword" : {
                    "type" : "keyword",
                    "ignore_above" : 256
                  }
                }
              },
              "timezone" : {
                "type" : "text",
                "fields" : {
                  "keyword" : {
                    "type" : "keyword",
                    "ignore_above" : 256
                  }
                }
              }
            }
          },
          "SrcIp" : { "type" : "ip" },
          "SrcPort" : {
            "type" : "long"
          },
          "TTL" : {
            "type" : "text",
            "fields" : {
              "keyword" : {
                "type" : "keyword",
                "ignore_above" : 256
              }
            }
          },
          "alert_description" : {
            "type" : "text",
            "fields" : {
              "keyword" : {
                "type" : "keyword",
                "ignore_above" : 256
              }
            }
          },
          "classification" : {
            "type" : "text",
            "fields" : {
              "keyword" : {
                "type" : "keyword",
                "ignore_above" : 256
              }
            }
          },
          "event_priority" : {
            "type" : "long"
          },
          "event_timestamp" : {
            "type" : "text",
            "fields" : {
              "keyword" : {
                "type" : "keyword",
                "ignore_above" : 256
              }
            }
          },
          "gid" : {
            "type" : "text",
            "fields" : {
              "keyword" : {
                "type" : "keyword",
                "ignore_above" : 256
              }
            }
          },
          "host" : {
            "type" : "text",
            "fields" : {
              "keyword" : {
                "type" : "keyword",
                "ignore_above" : 256
              }
            }
          },
          "message" : {
            "type" : "text",
            "fields" : {
              "keyword" : {
                "type" : "keyword",
                "ignore_above" : 256
              }
            }
          },
          "msg" : {
            "type" : "text",
            "fields" : {
              "keyword" : {
                "type" : "keyword",
                "ignore_above" : 256
              }
            }
          },
          "msg_source" : {
            "type" : "text",
            "fields" : {
              "keyword" : {
                "type" : "keyword",
                "ignore_above" : 256
              }
            }
          },
          "protocol" : {
            "type" : "text",
            "fields" : {
              "keyword" : {
                "type" : "keyword",
                "ignore_above" : 256
              }
            }
          },
          "rev" : {
            "type" : "text",
            "fields" : {
              "keyword" : {
                "type" : "keyword",
                "ignore_above" : 256
              }
            }
          },
          "rule_type" : {
            "type" : "text",
            "fields" : {
              "keyword" : {
                "type" : "keyword",
                "ignore_above" : 256
              }
            }
          },
          "sensor_name" : {
            "type" : "text",
            "fields" : {
              "keyword" : {
                "type" : "keyword",
                "ignore_above" : 256
              }
            }
          },
          "severity" : {
            "type" : "text",
            "fields" : {
              "keyword" : {
                "type" : "keyword",
                "ignore_above" : 256
              }
            }
          },
          "sid" : {
            "type" : "text",
            "fields" : {
              "keyword" : {
                "type" : "keyword",
                "ignore_above" : 256
              }
            }
          },
          "tags" : {
            "type" : "text",
            "fields" : {
              "keyword" : {
                "type" : "keyword",
                "ignore_above" : 256
              }
            }
          },
          "type" : {
            "type" : "text",
            "fields" : {
              "keyword" : {
                "type" : "keyword",
                "ignore_above" : 256
              }
            }
          }
        }
      }
    }
  }

